atom/__init__.py
atom/filters.py
atom/forms.py
atom/mixins.py
atom/models.py
atom/views.py
atom/ext/__init__.py
atom/ext/autocomplete_light/__init__.py
atom/ext/autocomplete_light/filters.py
atom/ext/contenttypes/__init__.py
atom/ext/contenttypes/serializers.py
atom/ext/crispy_forms/__init__.py
atom/ext/crispy_forms/filters.py
atom/ext/crispy_forms/forms.py
atom/ext/crispy_forms/views.py
atom/ext/django_filters/__init__.py
atom/ext/django_filters/filters.py
atom/ext/django_filters/views.py
atom/ext/guardian/__init__.py
atom/ext/guardian/forms.py
atom/ext/guardian/tests.py
atom/ext/guardian/views.py
atom/ext/rest_framework/__init__.py
atom/ext/rest_framework/mixins.py
atom/ext/sites/__init__.py
atom/ext/sites/serializers.py
atom/ext/slugify/__init__.py
atom/ext/slugify/slugifier.py
atom/ext/tinycontent/__init__.py
atom/ext/tinycontent/forms.py
atom/management/__init__.py
atom/management/commands/__init__.py
atom/management/commands/generate_factory.py
atom/management/commands/generate_routers.py
atom/management/commands/generate_serializers.py
atom/management/commands/generate_viewsets.py
atom/management/commands/generate_viewsets_tests.py
atom/templatetags/__init__.py
atom/templatetags/querystring_tags.py
django_atom-0.16.3.dist-info/METADATA
django_atom-0.16.3.dist-info/RECORD
django_atom-0.16.3.dist-info/WHEEL
django_atom-0.16.3.dist-info/top_level.txt
