Metadata-Version: 2.1
Name: django-atom
Version: 0.16.3
Summary: A different stuff for Django to faster make a world a better place.
Home-page: https://github.com/ad-m/django-atom
Author: Adam Dobrawy
Author-email: naczelnik@jawnosc.tk
License: BSD
Keywords: django-atom
Platform: UNKNOWN
Classifier: Development Status :: 2 - Pre-Alpha
Classifier: Framework :: Django
Classifier: Intended Audience :: Developers
Classifier: License :: OSI Approved :: BSD License
Classifier: Natural Language :: English
Classifier: Programming Language :: Python :: 2
Classifier: Programming Language :: Python :: 2.7
Classifier: Programming Language :: Python :: 3
Classifier: Programming Language :: Python :: 3.4
Classifier: Programming Language :: Python :: 3.5
Classifier: Programming Language :: Python :: 3.6
